spikesift/__init__.py
spikesift/_core.py
spikesift/core.py
spikesift/_cython/__init__.py
spikesift/_cython/alignment.c
spikesift/_cython/alignment.cp37-win_amd64.pyd
spikesift/_cython/alignment.pyx
spikesift/_cython/clustering.c
spikesift/_cython/clustering.cp37-win_amd64.pyd
spikesift/_cython/clustering.pyx
spikesift/_cython/detection.c
spikesift/_cython/detection.cp37-win_amd64.pyd
spikesift/_cython/detection.pyx
spikesift/_cython/preprocessing.c
spikesift/_cython/preprocessing.cp37-win_amd64.pyd
spikesift/_cython/preprocessing.pyx
spikesift/_cython/subtraction.c
spikesift/_cython/subtraction.cp37-win_amd64.pyd
spikesift/_cython/subtraction.pyx
tests/__init__.py
tests/test_map_clusters.py
tests/test_merge_recordings.py
tests/test_recording.py
tests/test_sorted_recording.py
spikesift-0.1.1.dist-info/LICENSE
spikesift-0.1.1.dist-info/METADATA
spikesift-0.1.1.dist-info/WHEEL
spikesift-0.1.1.dist-info/top_level.txt
spikesift-0.1.1.dist-info/RECORD
