Metadata-Version: 2.1
Name: spikesift
Version: 0.1.1
Summary: Real-time spike sorting for high-density extracellular recordings
Home-page: https://github.com/vasilisgeorgiadis/spikesift
Author: Vasileios Georgiadis
License: MIT
Classifier: Development Status :: 4 - Beta
Classifier: Intended Audience :: Science/Research
Classifier: Programming Language :: Python :: 3
Classifier: Programming Language :: Cython
Classifier: Operating System :: OS Independent
Requires-Python: >=3.7
License-File: LICENSE
Requires-Dist: numpy
Requires-Dist: scipy
Requires-Dist: tqdm
